DX_Extract/__init__.py
DX_Extract/extract.py
DX_Extract/Lib/__init__.py
DX_Extract/Lib/connect.py
DX_Extract/Lib/etl.py
DX_Extract/Lib/parameter.py
datax_etl-0.0.10.8.1.dist-info/METADATA
datax_etl-0.0.10.8.1.dist-info/WHEEL
datax_etl-0.0.10.8.1.dist-info/top_level.txt
datax_etl-0.0.10.8.1.dist-info/RECORD
