Metadata-Version: 2.4
Name: DATAx_ETL
Version: 0.0.10.8.1
Summary: APP de EXTRACT (E) do ETL da suite DATAx
Home-page: https://github.com/DE-DataEng/DATAx-ETL.git
Author: Almir J Gomes
Author-email: almir.jg@hotmail.com
Requires-Python: >=3.9
Requires-Dist: DE_Lib>=0.0.49.1
Requires-Dist: dotenv>=0.9.9
Dynamic: author
Dynamic: author-email
Dynamic: description
Dynamic: description-content-type
Dynamic: home-page
Dynamic: requires-dist
Dynamic: requires-python
Dynamic: summary
